ignite_simple/__init__.py
ignite_simple/analarams.py
ignite_simple/analysis.py
ignite_simple/dispatcher.py
ignite_simple/figure_utils.py
ignite_simple/helper.py
ignite_simple/hyperparams.py
ignite_simple/model_manager.py
ignite_simple/range_finder.py
ignite_simple/text_analysis.py
ignite_simple/trainer.py
ignite_simple/tuner.py
ignite_simple/utils.py
ignite_simple/vary_bs_loader.py
ignite_simple/gen_sweep/param_selectors.py
ignite_simple/gen_sweep/sweeper.py
ignite_simple-0.0.11.dist-info/LICENSE.txt
ignite_simple-0.0.11.dist-info/METADATA
ignite_simple-0.0.11.dist-info/WHEEL
ignite_simple-0.0.11.dist-info/top_level.txt
ignite_simple-0.0.11.dist-info/RECORD
