Metadata-Version: 2.1
Name: ignite-simple
Version: 0.0.11
Summary: Easily train pytorch models with automatic LR and BS tuning
Home-page: https://github.com/tjstretchalot/ignite-simple
Author: Timothy Moore
Author-email: mtimothy984@gmail.com
License: CC0
Keywords: torch pytorch models machine-learning learning-rate batch-size hyperparameters
Platform: UNKNOWN
Classifier: Programming Language :: Python :: 3
Classifier: Programming Language :: Python :: 3.6
Classifier: Programming Language :: Python :: 3.7
Classifier: License :: CC0 1.0 Universal (CC0 1.0) Public Domain Dedication
Classifier: Topic :: Utilities
Requires-Python: >=3.6
Requires-Dist: pca3dvis
Requires-Dist: torch
Requires-Dist: numpy
Requires-Dist: matplotlib
Requires-Dist: scipy
Requires-Dist: pyzmq
Requires-Dist: beautifulsoup4
Requires-Dist: pytorch-ignite
Requires-Dist: psutil
Requires-Dist: sortedcontainers
